[  
	{ "display_id":1, "display_text":"Do you have the power to make free choices?", "y_outcome":"index.html?target=2", "n_outcome":"index.html?target=2", "y_display":"Yes", "n_display":"No"  },
	{ "display_id":2, "display_text":"Is there any objective truth?", "y_outcome":"index.html?target=4", "n_outcome":"index.html?target=3", "y_display":"Yes", "n_display":"No" },
	{ "display_id":3, "display_text":"Worldview: Relativism", "y_outcome":"index.html", "n_outcome":"index.html?target=2", "y_display":"Back to Start", "n_display":"Back"  },
	{ "display_id":4, "display_text":"Is it possible to know the truth?", "y_outcome":"index.html?target=6", "n_outcome":"index.html?target=5", "y_display":"Yes", "n_display":"No" },
	{ "display_id":5, "display_text":"Worldview: Skepticism", "y_outcome":"index.html", "n_outcome":"index.html?target=4", "y_display":"Back to Start", "n_display":"Back" },
	{ "display_id":6, "display_text":"Is anything objectively good or bad?","y_outcome":"index.html?target=8", "n_outcome":"index.html?target=7", "y_display":"Yes", "n_display":"No" },
	{ "display_id":7, "display_text":"Worldview: Nihilism",  "y_outcome":"index.html", "n_outcome":"index.html?target=6", "y_display":"Back to Start", "n_display":"Back" },
	{ "display_id":8, "display_text":"Is there more than one valid religion?","y_outcome":"index.html?target=9", "n_outcome":"index.html?target=10", "y_display":"Yes", "n_display":"No" },
	{ "display_id":9, "display_text":"Worldview: Pluralism", "y_outcome":"index.html", "n_outcome":"index.html?target=8", "y_display":"Back to Start", "n_display":"Back" },
	{ "display_id":10, "display_text":"Is there a God?","y_outcome":"index.html?target=12", "n_outcome":"index.html?target=11", "y_display":"Yes", "n_display":"No"  },
	{ "display_id":11, "display_text":"Worldview: Atheism", "y_outcome":"index.html", "n_outcome":"index.html?target=10", "y_display":"Back to Start", "n_display":"Back"  },
	{ "display_id":12, "display_text":"Entering Theistic Worldviews.", "y_outcome":"index.html?target=13", "n_outcome":"index.html", "y_display":"Go on", "n_display":"Back to Start"  },
	{ "display_id":13, "display_text":"Is God a personal being?", "y_outcome":"index.html?target=14", "n_outcome":"index.html?target=15", "y_display":"Yes", "n_display":"No" },
	{ "display_id":14, "display_text":"Is God a perfect being?", "y_outcome":"index.html?target=16", "n_outcome":"index.html?target=17", "y_display":"Yes", "n_display":"No" },
	{ "display_id":15, "display_text":"Entering Quasi-Theistic Worldviews", "y_outcome":"index.html?target=24", "n_outcome":"index.html", "y_display":"Go on", "n_display":"Back to Start"  },
	{ "display_id":16, "display_text":"Has God communicated with humans?", "y_outcome":"index.html?target=18", "n_outcome":"index.html?target=19", "y_display":"Yes", "n_display":"No" },
	{ "display_id":17, "display_text":"Entering Finite Theistic Worldviews", "y_outcome":"index.html?target=21", "n_outcome":"index.html", "y_display":"Go on", "n_display":"Back to Start"  },
	{ "display_id":18, "display_text":"Has God communicated openly to humans?", "y_outcome":"index.html?target=20", "n_outcome":"index.html?target=19", "y_display":"Yes", "n_display":"No" },
	{ "display_id":19, "display_text":"Worldview: Mysticism", "y_outcome":"index.html", "n_outcome":"index.html?target=18", "y_display":"Back to Start", "n_display":"Back"  },
	{ "display_id":20, "display_text":"Did Jesus of Nazareth rise from the dead?", "y_outcome":"index.html?target=29", "n_outcome":"index.html?target=30", "y_display":"Yes", "n_display":"No" },
	{ "display_id":21, "display_text":"Is there only one God?", "y_outcome":"index.html?target=22", "n_outcome":"index.html?target=23", "y_display":"Yes", "n_display":"No" },
	{ "display_id":22, "display_text":"Worldview: Finite Godism", "y_outcome":"index.html", "n_outcome":"index.html?target=21", "y_display":"Back to Start", "n_display":"Back"  },
	{ "display_id":23, "display_text":"Worldview: Polytheism", "y_outcome":"index.html", "n_outcome":"index.html?target=22", "y_display":"Back to Start", "n_display":"Back"  },
	{ "display_id":24, "display_text":"Is the universe God?", "y_outcome":"index.html?target=25", "n_outcome":"index.html?target=26", "y_display":"Yes", "n_display":"No" },
	{ "display_id":25, "display_text":"Worldview: Pantheism", "y_outcome":"index.html", "n_outcome":"index.html?target=24", "y_display":"Back to Start", "n_display":"Back"  },
	{ "display_id":26, "display_text":"Is the universe within God?", "y_outcome":"index.html?target=27", "n_outcome":"index.html?target=28", "y_display":"Yes", "n_display":"No" },
	{ "display_id":27, "display_text":"Worldview: Polytheism", "y_outcome":"index.html", "n_outcome":"index.html?target=26", "y_display":"Back to Start", "n_display":"Back"  },
	{ "display_id":28, "display_text":"Worldview: Platonism", "y_outcome":"index.html", "n_outcome":"index.html?target=26", "y_display":"Back to Start", "n_display":"Back"  },
	{ "display_id":29, "display_text":"Was Jesus of Nazareth divine?", "y_outcome":"index.html?target=36", "n_outcome":"index.html?target=38", "y_display":"Yes", "n_display":"No" },
	{ "display_id":30, "display_text":"Entering Non-Christian Theistic Worldviews", "y_outcome":"index.html?target=31", "n_outcome":"index.html", "y_display":"Go on", "n_display":"Back to Start"  },
	{ "display_id":31, "display_text":"Was Muhammad a true prophet of God?", "y_outcome":"index.html?target=32", "n_outcome":"index.html?target=33", "y_display":"Yes", "n_display":"No" },
	{ "display_id":32, "display_text":"Worldview: Islam", "y_outcome":"index.html", "n_outcome":"index.html?target=31", "y_display":"Back to Start", "n_display":"Back"  },
	{ "display_id":33, "display_text":"Was Moses a true prophet of God?", "y_outcome":"index.html?target=34", "n_outcome":"index.html?target=35", "y_display":"Yes", "n_display":"No" },
	{ "display_id":34, "display_text":"Worldview: Judism", "y_outcome":"index.html", "n_outcome":"index.html?target=33", "y_display":"Back to Start", "n_display":"Back"  },
	{ "display_id":35, "display_text":"Worldview: Islam", "y_outcome":"index.html", "n_outcome":"index.html?target=33", "y_display":"Back to Start", "n_display":"Back"  },
	{ "display_id":36, "display_text":"Do good people go to heaven and bad people to hell?", "y_outcome":"index.html?target=37", "n_outcome":"index.html?target=39", "y_display":"Yes", "n_display":"No" },
	{ "display_id":37, "display_text":"Worldview: Pelagianism", "y_outcome":"index.html", "n_outcome":"index.html?target=26", "y_display":"Back to Start", "n_display":"Back"  },
	{ "display_id":38, "display_text":"Worldview: Unitarianism", "y_outcome":"index.html", "n_outcome":"index.html?target=29", "y_display":"Back to Start", "n_display":"Back"  },
	{ "display_id":39, "display_text":"Worldview: Christianity", "y_outcome":"index.html", "n_outcome":"index.html?target=36", "y_display":"Back to Start", "n_display":"Back"  },
	{ "display_id":40, "display_text":"Worldview: Polytheism", "y_outcome":"index.html", "n_outcome":"index.html?target=26", "y_display":"Back to Start", "n_display":"Back"  }
]